{
  "project_info": {
    "project_number": "768535192232",
    "project_id": "demofirebasesetup-5b2da",
    "storage_bucket": "demofirebasesetup-5b2da.appspot.com"
  },
  "client": [
    {
      "client_info": {
        "mobilesdk_app_id": "1:768535192232:android:1dd0957b32ce1ec295589d",
        "android_client_info": {
          "package_name": "com.example.flutter_firebase_work"
        }
      },
      "oauth_client": [
        {
          "client_id": "768535192232-6flkm2rm1bmbn6vdo031tgrcog9v8hsr.apps.googleusercontent.com",
          "client_type": 3
        }
      ],
      "api_key": [
        {
          "current_key": "AIzaSyCRAgV--KC5rR_u7rQ8FTL9AJHCEF8Nrtw"
        }
      ],
      "services": {
        "appinvite_service": {
          "other_platform_oauth_client": [
            {
              "client_id": "768535192232-6flkm2rm1bmbn6vdo031tgrcog9v8hsr.apps.googleusercontent.com",
              "client_type": 3
            }
          ]
        }
      }
    }
  ],
  "configuration_version": "1"
}